[{"plant":"asdfdgf","name":"dsfdgh","position":"director","rate":500,"hours":8,"bonus":567,"arr":[[{"name":"dgfhj","rate":17,"hours":8,"bonus":123,"arr":[]},{"name":"vnbm","rate":17,"hours":8,"bonus":123,"arr":[]},{"name":"xgc","rate":17,"hours":8,"bonus":123,"arr":[]}]],"superbonus":3456},{"plant":"discaveri","name":"mozart","position":"director","rate":500,"hours":8,"bonus":567,"arr":[[{"name":"zxc","rate":17,"hours":8,"bonus":123,"arr":[]},{"name":"vbn","rate":17,"hours":8,"bonus":123,"arr":[]},{"name":"nm,","rate":17,"hours":8,"bonus":123,"arr":[]}]],"superbonus":3456},{"plant":"adsc","name":"dsfvd","position":"director","rate":500,"hours":8,"bonus":567,"arr":[[]],"superbonus":3456},{"plant":"wwwwwwwwwwwwwwwww","name":"eeeeeeeeeeeeeeeeeeeee","position":"director","rate":500,"hours":8,"bonus":567,"arr":[[{"name":"","rate":17,"hours":8,"bonus":123,"arr":[]},{"name":"dsf","rate":17,"hours":8,"bonus":123,"arr":[]},{"name":"dfsd","rate":17,"hours":8,"bonus":123,"arr":[]},{"name":"","rate":17,"hours":8,"bonus":123,"arr":[]},{"name":"","rate":17,"hours":8,"bonus":123,"arr":[]},{"name":"","rate":17,"hours":8,"bonus":123,"arr":[]},{"name":"","rate":17,"hours":8,"bonus":123,"arr":[]},{"name":"","rate":17,"hours":8,"bonus":123,"arr":[]},{"name":"","rate":17,"hours":8,"bonus":123,"arr":[]},{"name":"","rate":17,"hours":8,"bonus":123,"arr":[]},{"name":"","rate":17,"hours":8,"bonus":123,"arr":[]},{"name":"fdgsf","rate":17,"hours":8,"bonus":123,"arr":[]},{"name":"fadgsfbhn","rate":17,"hours":8,"bonus":123,"arr":[]},{"name":"","rate":17,"hours":8,"bonus":123,"arr":[]},{"name":"","rate":17,"hours":8,"bonus":123,"arr":[]},{"name":"","rate":17,"hours":8,"bonus":123,"arr":[]},{"name":"","rate":17,"hours":8,"bonus":123,"arr":[]},{"name":"","rate":17,"hours":8,"bonus":123,"arr":[]},{"name":"","rate":17,"hours":8,"bonus":123,"arr":[]},{"name":"","rate":17,"hours":8,"bonus":123,"arr":[]},{"name":"","rate":17,"hours":8,"bonus":123,"arr":[]},{"name":"","rate":17,"hours":8,"bonus":123,"arr":[]},{"name":"","rate":17,"hours":8,"bonus":123,"arr":[]},{"name":"","rate":17,"hours":8,"bonus":123,"arr":[]},{"name":"","rate":17,"hours":8,"bonus":123,"arr":[]},{"name":"","rate":17,"hours":8,"bonus":123,"arr":[]},{"name":"","rate":17,"hours":8,"bonus":123,"arr":[]},{"name":"","rate":17,"hours":8,"bonus":123,"arr":[]},{"name":"","rate":17,"hours":8,"bonus":123,"arr":[]},{"name":"","rate":17,"hours":8,"bonus":123,"arr":[]},{"name":"","rate":17,"hours":8,"bonus":123,"arr":[]},{"name":"","rate":17,"hours":8,"bonus":123,"arr":[]},{"name":"","rate":17,"hours":8,"bonus":123,"arr":[]},{"name":"","rate":17,"hours":8,"bonus":123,"arr":[]},{"name":"","rate":17,"hours":8,"bonus":123,"arr":[]},{"name":"","rate":17,"hours":8,"bonus":123,"arr":[]},{"name":"","rate":17,"hours":8,"bonus":123,"arr":[]},{"name":"","rate":17,"hours":8,"bonus":123,"arr":[]},{"name":"","rate":17,"hours":8,"bonus":123,"arr":[]},{"name":"","rate":17,"hours":8,"bonus":123,"arr":[]},{"name":"","rate":17,"hours":8,"bonus":123,"arr":[]},{"name":"","rate":17,"hours":8,"bonus":123,"arr":[]},{"name":"","rate":17,"hours":8,"bonus":123,"arr":[]},{"name":"","rate":17,"hours":8,"bonus":123,"arr":[]},{"name":"","rate":17,"hours":8,"bonus":123,"arr":[]},{"name":"","rate":17,"hours":8,"bonus":123,"arr":[]},{"name":"","rate":17,"hours":8,"bonus":123,"arr":[]},{"name":"","rate":17,"hours":8,"bonus":123,"arr":[]},{"name":"","rate":17,"hours":8,"bonus":123,"arr":[]},{"name":"","rate":17,"hours":8,"bonus":123,"arr":[]},{"name":"","rate":17,"hours":8,"bonus":123,"arr":[]},{"name":"","rate":17,"hours":8,"bonus":123,"arr":[]},{"name":"","rate":17,"hours":8,"bonus":123,"arr":[]},{"name":"","rate":17,"hours":8,"bonus":123,"arr":[]},{"name":"","rate":17,"hours":8,"bonus":123,"arr":[]},{"name":"","rate":17,"hours":8,"bonus":123,"arr":[]},{"name":"","rate":17,"hours":8,"bonus":123,"arr":[]},{"name":"","rate":17,"hours":8,"bonus":123,"arr":[]},{"name":"","rate":17,"hours":8,"bonus":123,"arr":[]},{"name":"","rate":17,"hours":8,"bonus":123,"arr":[]},{"name":"fdbx","rate":17,"hours":8,"bonus":123,"arr":[]},{"name":"","rate":17,"hours":8,"bonus":123,"arr":[]},{"name":"","rate":17,"hours":8,"bonus":123,"arr":[]},{"name":"","rate":17,"hours":8,"bonus":123,"arr":[]},{"name":"","rate":17,"hours":8,"bonus":123,"arr":[]},{"name":"","rate":17,"hours":8,"bonus":123,"arr":[]},{"name":"","rate":17,"hours":8,"bonus":123,"arr":[]},{"name":"","rate":17,"hours":8,"bonus":123,"arr":[]},{"name":"","rate":17,"hours":8,"bonus":123,"arr":[]},{"name":"","rate":17,"hours":8,"bonus":123,"arr":[]},{"name":"","rate":17,"hours":8,"bonus":123,"arr":[]},{"name":"","rate":17,"hours":8,"bonus":123,"arr":[]},{"name":"","rate":17,"hours":8,"bonus":123,"arr":[]},{"name":"","rate":17,"hours":8,"bonus":123,"arr":[]},{"name":"","rate":17,"hours":8,"bonus":123,"arr":[]},{"name":"","rate":17,"hours":8,"bonus":123,"arr":[]},{"name":"","rate":17,"hours":8,"bonus":123,"arr":[]},{"name":"","rate":17,"hours":8,"bonus":123,"arr":[]},{"name":"","rate":17,"hours":8,"bonus":123,"arr":[]},{"name":"","rate":17,"hours":8,"bonus":123,"arr":[]},{"name":"","rate":17,"hours":8,"bonus":123,"arr":[]},{"name":"","rate":17,"hours":8,"bonus":123,"arr":[]},{"name":"","rate":17,"hours":8,"bonus":123,"arr":[]},{"name":"","rate":17,"hours":8,"bonus":123,"arr":[]},{"name":"","rate":17,"hours":8,"bonus":123,"arr":[]},{"name":"","rate":17,"hours":8,"bonus":123,"arr":[]},{"name":"","rate":17,"hours":8,"bonus":123,"arr":[]},{"name":"","rate":17,"hours":8,"bonus":123,"arr":[]},{"name":"","rate":17,"hours":8,"bonus":123,"arr":[]},{"name":"","rate":17,"hours":8,"bonus":123,"arr":[]},{"name":"","rate":17,"hours":8,"bonus":123,"arr":[]},{"name":"","rate":17,"hours":8,"bonus":123,"arr":[]},{"name":"","rate":17,"hours":8,"bonus":123,"arr":[]},{"name":"","rate":17,"hours":8,"bonus":123,"arr":[]},{"name":"","rate":17,"hours":8,"bonus":123,"arr":[]},{"name":"","rate":17,"hours":8,"bonus":123,"arr":[]},{"name":"","rate":17,"hours":8,"bonus":123,"arr":[]},{"name":"","rate":17,"hours":8,"bonus":123,"arr":[]},{"name":"","rate":17,"hours":8,"bonus":123,"arr":[]},{"name":"","rate":17,"hours":8,"bonus":123,"arr":[]}]],"superbonus":3456}]